duckdb_upgrade/.gitignore
duckdb_upgrade/__init__.py
duckdb_upgrade/__main__.py
duckdb_upgrade/data/version_map.json
duckdb_upgrade/platform.py
duckdb_upgrade/versions.py
duckdb_upgrade-0.8.0.dist-info/WHEEL
duckdb_upgrade-0.8.0.dist-info/entry_points.txt
duckdb_upgrade-0.8.0.dist-info/METADATA
duckdb_upgrade-0.8.0.dist-info/RECORD
