Metadata-Version: 2.3
Name: duckdb-upgrade
Version: 0.8.0
Summary: A tool to upgrade DuckDB database files.
Author: Nick Pleatsikas
Author-email: Nick Pleatsikas <nick@pleatsikas.me>
License: MIT
Requires-Dist: packaging>=23.1
Requires-Dist: requests>=2.31.0
Requires-Python: >=3.8
